muapi_client_py/__init__.py
muapi_client_py/cli.py
muapi_client_py-0.1.3.2.dist-info/METADATA
muapi_client_py-0.1.3.2.dist-info/WHEEL
muapi_client_py-0.1.3.2.dist-info/top_level.txt
muapi_client_py-0.1.3.2.dist-info/RECORD
