Metadata-Version: 2.1
Name: muapi-client-py
Version: 0.1.3.2
Summary: Client library for Mongo Upload API server
Home-page: UNKNOWN
Author: AlexeiSimonov
Author-email: sushka2820655@yandex.ru
License: MIT
Platform: UNKNOWN
Requires-Dist: requests
